{
     "player1": {
          "name": "Foo",
          "capturedPieces": [
               {
                    "color": -1,
                    "moved": true,
                    "type": "Pawn"
               },
               {
                    "color": -1,
                    "moved": false,
                    "type": "Pawn"
               },
               {
                    "color": -1,
                    "moved": false,
                    "type": "Pawn"
               },
               {
                    "color": -1,
                    "moved": false,
                    "type": "Pawn"
               },
               {
                    "color": -1,
                    "moved": false,
                    "type": "Pawn"
               },
               {
                    "color": -1,
                    "moved": false,
                    "type": "Pawn"
               },
               {
                    "color": -1,
                    "moved": false,
                    "type": "Pawn"
               },
               {
                    "color": -1,
                    "moved": false,
                    "type": "Pawn"
               },
               {
                    "color": -1,
                    "moved": false,
                    "type": "Rook"
               },
               {
                    "color": -1,
                    "moved": false,
                    "type": "Knight"
               },
               {
                    "color": -1,
                    "moved": false,
                    "type": "Bishop"
               },
               {
                    "color": -1,
                    "moved": false,
                    "type": "Bishop"
               },
               {
                    "color": -1,
                    "moved": false,
                    "type": "Knight"
               },
               {
                    "color": -1,
                    "moved": false,
                    "type": "Rook"
               },
               {
                    "color": -1,
                    "moved": true,
                    "type": "Queen"
               }
          ]
     },
     "player2": {
          "name": "Bar",
          "capturedPieces": [
               {
                    "color": 1,
                    "moved": true,
                    "type": "Pawn"
               },
               {
                    "color": 1,
                    "moved": false,
                    "type": "Pawn"
               },
               {
                    "color": 1,
                    "moved": false,
                    "type": "Pawn"
               },
               {
                    "color": 1,
                    "moved": false,
                    "type": "Pawn"
               },
               {
                    "color": 1,
                    "moved": false,
                    "type": "Pawn"
               },
               {
                    "color": 1,
                    "moved": false,
                    "type": "Pawn"
               },
               {
                    "color": 1,
                    "moved": false,
                    "type": "Rook"
               },
               {
                    "color": 1,
                    "moved": false,
                    "type": "Knight"
               },
               {
                    "color": 1,
                    "moved": false,
                    "type": "Bishop"
               },
               {
                    "color": 1,
                    "moved": false,
                    "type": "Pawn"
               },
               {
                    "color": 1,
                    "moved": false,
                    "type": "Pawn"
               },
               {
                    "color": 1,
                    "moved": false,
                    "type": "Rook"
               },
               {
                    "color": 1,
                    "moved": false,
                    "type": "Knight"
               },
               {
                    "color": 1,
                    "moved": false,
                    "type": "Bishop"
               },
               {
                    "color": 1,
                    "moved": true,
                    "type": "Queen"
               }
          ]
     },
     "state": 0,
     "board": {"board": [
          [
               {
                    "file": 0,
                    "piece": null,
                    "rank": 0
               },
               {
                    "file": 1,
                    "piece": null,
                    "rank": 0
               },
               {
                    "file": 2,
                    "piece": null,
                    "rank": 0
               },
               {
                    "file": 3,
                    "piece": null,
                    "rank": 0
               },
               {
                    "file": 4,
                    "piece": null,
                    "rank": 0
               },
               {
                    "file": 5,
                    "piece": null,
                    "rank": 0
               },
               {
                    "file": 6,
                    "piece": null,
                    "rank": 0
               },
               {
                    "file": 7,
                    "piece": null,
                    "rank": 0
               }
          ],
          [
               {
                    "file": 0,
                    "piece": null,
                    "rank": 1
               },
               {
                    "file": 1,
                    "piece": null,
                    "rank": 1
               },
               {
                    "file": 2,
                    "piece": null,
                    "rank": 1
               },
               {
                    "file": 3,
                    "piece": null,
                    "rank": 1
               },
               {
                    "file": 4,
                    "piece": null,
                    "rank": 1
               },
               {
                    "file": 5,
                    "piece": null,
                    "rank": 1
               },
               {
                    "file": 6,
                    "piece": null,
                    "rank": 1
               },
               {
                    "file": 7,
                    "piece": null,
                    "rank": 1
               }
          ],
          [
               {
                    "file": 0,
                    "piece": null,
                    "rank": 2
               },
               {
                    "file": 1,
                    "piece": null,
                    "rank": 2
               },
               {
                    "file": 2,
                    "piece": null,
                    "rank": 2
               },
               {
                    "file": 3,
                    "piece": null,
                    "rank": 2
               },
               {
                    "file": 4,
                    "piece": null,
                    "rank": 2
               },
               {
                    "file": 5,
                    "piece": null,
                    "rank": 2
               },
               {
                    "file": 6,
                    "piece": null,
                    "rank": 2
               },
               {
                    "file": 7,
                    "piece": null,
                    "rank": 2
               }
          ],
          [
               {
                    "file": 0,
                    "piece": null,
                    "rank": 3
               },
               {
                    "file": 1,
                    "piece": null,
                    "rank": 3
               },
               {
                    "file": 2,
                    "piece": null,
                    "rank": 3
               },
               {
                    "file": 3,
                    "piece": {
                         "color": -1,
                         "moved": true,
                         "type": "King"
                    },
                    "rank": 3
               },
               {
                    "file": 4,
                    "piece": null,
                    "rank": 3
               },
               {
                    "file": 5,
                    "piece": null,
                    "rank": 3
               },
               {
                    "file": 6,
                    "piece": null,
                    "rank": 3
               },
               {
                    "file": 7,
                    "piece": null,
                    "rank": 3
               }
          ],
          [
               {
                    "file": 0,
                    "piece": null,
                    "rank": 4
               },
               {
                    "file": 1,
                    "piece": null,
                    "rank": 4
               },
               {
                    "file": 2,
                    "piece": null,
                    "rank": 4
               },
               {
                    "file": 3,
                    "piece": null,
                    "rank": 4
               },
               {
                    "file": 4,
                    "piece": {
                         "color": 1,
                         "moved": true,
                         "type": "King"
                    },
                    "rank": 4
               },
               {
                    "file": 5,
                    "piece": null,
                    "rank": 4
               },
               {
                    "file": 6,
                    "piece": null,
                    "rank": 4
               },
               {
                    "file": 7,
                    "piece": null,
                    "rank": 4
               }
          ],
          [
               {
                    "file": 0,
                    "piece": null,
                    "rank": 5
               },
               {
                    "file": 1,
                    "piece": null,
                    "rank": 5
               },
               {
                    "file": 2,
                    "piece": null,
                    "rank": 5
               },
               {
                    "file": 3,
                    "piece": null,
                    "rank": 5
               },
               {
                    "file": 4,
                    "piece": null,
                    "rank": 5
               },
               {
                    "file": 5,
                    "piece": null,
                    "rank": 5
               },
               {
                    "file": 6,
                    "piece": null,
                    "rank": 5
               },
               {
                    "file": 7,
                    "piece": null,
                    "rank": 5
               }
          ],
          [
               {
                    "file": 0,
                    "piece": null,
                    "rank": 6
               },
               {
                    "file": 1,
                    "piece": null,
                    "rank": 6
               },
               {
                    "file": 2,
                    "piece": null,
                    "rank": 6
               },
               {
                    "file": 3,
                    "piece": null,
                    "rank": 6
               },
               {
                    "file": 4,
                    "piece": null,
                    "rank": 6
               },
               {
                    "file": 5,
                    "piece": null,
                    "rank": 6
               },
               {
                    "file": 6,
                    "piece": null,
                    "rank": 6
               },
               {
                    "file": 7,
                    "piece": null,
                    "rank": 6
               }
          ],
          [
               {
                    "file": 0,
                    "piece": null,
                    "rank": 7
               },
               {
                    "file": 1,
                    "piece": null,
                    "rank": 7
               },
               {
                    "file": 2,
                    "piece": null,
                    "rank": 7
               },
               {
                    "file": 3,
                    "piece": null,
                    "rank": 7
               },
               {
                    "file": 4,
                    "piece": null,
                    "rank": 7
               },
               {
                    "file": 5,
                    "piece": null,
                    "rank": 7
               },
               {
                    "file": 6,
                    "piece": null,
                    "rank": 7
               },
               {
                    "file": 7,
                    "piece": null,
                    "rank": 7
               }
          ]
     ]},
     "turns": 24
}